executor/safe_queue.py
thread_executor-0.1.3.dist-info/LICENSE
thread_executor-0.1.3.dist-info/METADATA
thread_executor-0.1.3.dist-info/WHEEL
thread_executor-0.1.3.dist-info/RECORD
