Metadata-Version: 2.1
Name: thread-executor
Version: 0.1.3
Summary: A Python library for executing tasks in parallel with threads and queues
Home-page: https://pypi.org/project/thread-executor
Keywords: multi thread,threading,concurency,worker pool
Author: TuanDC
Author-email: tuandao864@gmail.com
Maintainer: TuanDC
Maintainer-email: tuandao864@gmail.com
Requires-Python: >=3.6.2,<4.0.0
Classifier: Programming Language :: Python :: 3
Classifier: Programming Language :: Python :: 3.7
Classifier: Programming Language :: Python :: 3.8
Classifier: Programming Language :: Python :: 3.9
Classifier: Programming Language :: Python :: 3.10
Classifier: Programming Language :: Python :: 3.11
Classifier: Programming Language :: Python :: 3.12
Requires-Dist: loguru (>=0.6.0,<0.7.0)
Project-URL: Repository, https://github.com/bacsiTuan/executor
